svglib/__init__.py
svglib/svglib.py
svglib/utils.py
svglib-0.9.0b0.data/scripts/svg2pdf
svglib-0.9.0b0.dist-info/DESCRIPTION.rst
svglib-0.9.0b0.dist-info/METADATA
svglib-0.9.0b0.dist-info/RECORD
svglib-0.9.0b0.dist-info/WHEEL
svglib-0.9.0b0.dist-info/metadata.json
svglib-0.9.0b0.dist-info/top_level.txt
