Metadata-Version: 2.0
Name: svglib
Version: 0.9.0b0
Summary: A pure-Python library for reading and converting SVG
Home-page: https://github.com/deeplook/svglib
Author: Dinu Gherman
Author-email: gherman@darwin.in-berlin.de
License: LGPL 3
Keywords: SVG,PDF,reportlab,conversion,graphics
Platform: Posix
Platform: Windows
Classifier: Development Status :: 4 - Beta
Classifier: Environment :: Console
Classifier: Intended Audience :: End Users/Desktop
Classifier: Intended Audience :: Developers
Classifier: License :: OSI Approved :: GNU Lesser General Public License v3 (LGPLv3)
Classifier: Operating System :: MacOS :: MacOS X
Classifier: Operating System :: POSIX
Classifier: Natural Language :: English
Classifier: Programming Language :: Python
Classifier: Programming Language :: Python :: 2.7
Classifier: Programming Language :: Python :: 3.5
Classifier: Programming Language :: Python :: 3.6
Classifier: Programming Language :: Python :: 3.7
Classifier: Topic :: Documentation
Classifier: Topic :: Utilities
Classifier: Topic :: Printing
Classifier: Topic :: Multimedia :: Graphics :: Graphics Conversion
Classifier: Topic :: Software Development :: Libraries :: Python Modules
Classifier: Topic :: Text Processing :: Markup :: XML
Requires-Dist: reportlab
Requires-Dist: lxml
Requires-Dist: tinycss2 (>=0.6.0)
Requires-Dist: cssselect2 (>=0.2.0)
